{
  "id" : "dRuZopNu",
  "url" : "https://kurier.at/politik/inland/justiministerin-zadic-wurde-am-dreikoenigstag-mutter/401150106",
  "category" : "POLITICS",
  "publisher" : "kurier.at",
  "publishedOn" : "2021-01-08T14:31:41Z[UTC]",
  "author" : "raffaela.lindorfer@kurier.at (Raffaela Lindorfer)",
  "imageUrl" : "https://image.kurier.at/images/original/4860864/46-155063238.jpg",
  "sourceCountry" : "austria",
  "sourceLanguage" : "german",
  "targetLanguage" : "turkish",
  "articleTitle" : "Justiministerin Zadić bekam am Dreikönigstag ihr Baby",
  "articleTitleTranslated" : "Adalet Bakanı Zadić bebeğini Epifani'de doğurdu",
  "articleContent" : [ "Die Justiministerin wurde am 6. Jänner zum ersten Mal Mutter - es ist ein Bub. Vizekanzler Kogler hat bereits ihr Ressort übernommen." ],
  "articleContentTranslated" : [ "Adalet Bakanı ilk defa 6 Ocak'ta anne oldu - o bir erkek. Şansölye Yardımcısı Kogler portföyünü çoktan devraldı." ]
}